nice_tools/__init__.py
nice_tools/func_tools.py
nice_tools/http_base_client.py
nice_tools/logger_tools.py
nice_tools/thread_tools.py
nice_tools-0.0.6.dist-info/METADATA
nice_tools-0.0.6.dist-info/WHEEL
nice_tools-0.0.6.dist-info/top_level.txt
nice_tools-0.0.6.dist-info/RECORD
