Metadata-Version: 2.1
Name: nice-tools
Version: 0.0.6
Summary: A collection of tools for python
Home-page: https://github.com/amiwrpremium/nice_tools
Author: amiwrpremium
Author-email: amiwrpremium@gmail.com
License: MIT
Project-URL: Bug Tracker, https://github.com/amiwrpremium/nice_tools/issues
Keywords: tools,threading,thread,logging,logger
Classifier: Development Status :: 3 - Alpha
Classifier: Intended Audience :: Developers
Classifier: Topic :: Software Development :: Build Tools
Classifier: License :: OSI Approved :: MIT License
Classifier: Programming Language :: Python :: 3
Classifier: Programming Language :: Python :: 3.4
Classifier: Programming Language :: Python :: 3.5
Classifier: Programming Language :: Python :: 3.6
Classifier: Programming Language :: Python :: 3.7
Classifier: Programming Language :: Python :: 3.8
Classifier: Programming Language :: Python :: 3.9
Requires-Python: >=3.6
Requires-Dist: python-telegram-bot (==13.11)
Requires-Dist: requests
Requires-Dist: aiohttp
